{
	"metrics": [
	  {
		"id": "class specific specificity",
		"highValueBetter": true,
		"isScalarMetric": false,
		"isClassSpecific": true
	  },
	  {
		"id": "median class specific f0.5score",
		"highValueBetter": false,
		"isScalarMetric": true,
		"isClassSpecific": false
	  },
	  {
		"id": "avg class specific f0.5score",
		"highValueBetter": false,
		"isScalarMetric": true,
		"isClassSpecific": false
	  },
	  {
		"id": "weighted avg class specific f0.5score",
		"highValueBetter": false,
		"isScalarMetric": true,
		"isClassSpecific": false
	  },
	  {
		"id": "class specific f1score",
		"highValueBetter": false,
		"isScalarMetric": false,
		"isClassSpecific": true
	  },
	  {
		"id": "avg class specific f2score",
		"highValueBetter": false,
		"isScalarMetric": true,
		"isClassSpecific": false
	  },
	  {
		"id": "avg class specific accuracy",
		"highValueBetter": true,
		"isScalarMetric": true,
		"isClassSpecific": false
	  },
	  {
		"id": "accuracy",
		"highValueBetter": true,
		"isScalarMetric": true,
		"isClassSpecific": false
	  },
	  {
		"id": "avg diff to max class dummy of class specific precision",
		"highValueBetter": true,
		"isScalarMetric": true,
		"isClassSpecific": false
	  },
	  {
		"id": "avg diff to max class dummy of class specific f2score",
		"highValueBetter": false,
		"isScalarMetric": true,
		"isClassSpecific": false
	  },
	  {
		"id": "avg diff to max class dummy of class specific f1score",
		"highValueBetter": false,
		"isScalarMetric": true,
		"isClassSpecific": false
	  },
	  {
		"id": "avg class specific precision",
		"highValueBetter": true,
		"isScalarMetric": true,
		"isClassSpecific": false
	  },
	  {
		"id": "avg diff to max class dummy of class specific specificity",
		"highValueBetter": true,
		"isScalarMetric": true,
		"isClassSpecific": false
	  },
	  {
		"id": "median class specific precision",
		"highValueBetter": true,
		"isScalarMetric": true,
		"isClassSpecific": false
	  },
	  {
		"id": "max class specific f0.5score",
		"highValueBetter": false,
		"isScalarMetric": true,
		"isClassSpecific": false
	  },
	  {
		"id": "median class specific accuracy",
		"highValueBetter": true,
		"isScalarMetric": true,
		"isClassSpecific": false
	  },
	  {
		"id": "class specific f2score",
		"highValueBetter": false,
		"isScalarMetric": false,
		"isClassSpecific": true
	  },
	  {
		"id": "max class specific precision",
		"highValueBetter": true,
		"isScalarMetric": true,
		"isClassSpecific": false
	  },
	  {
		"id": "median class specific recall",
		"highValueBetter": true,
		"isScalarMetric": true,
		"isClassSpecific": false
	  },
	  {
		"id": "median class specific specificity",
		"highValueBetter": true,
		"isScalarMetric": true,
		"isClassSpecific": false
	  },
	  {
		"id": "max class specific accuracy",
		"highValueBetter": true,
		"isScalarMetric": true,
		"isClassSpecific": false
	  },
	  {
		"id": "avg diff to max class dummy of class specific f0.5score",
		"highValueBetter": false,
		"isScalarMetric": true,
		"isClassSpecific": false
	  },
	  {
		"id": "min class specific precision",
		"highValueBetter": true,
		"isScalarMetric": true,
		"isClassSpecific": false
	  },
	  {
		"id": "max class specific recall",
		"highValueBetter": true,
		"isScalarMetric": true,
		"isClassSpecific": false
	  },
	  {
		"id": "max class specific f1score",
		"highValueBetter": false,
		"isScalarMetric": true,
		"isClassSpecific": false
	  },
	  {
		"id": "avg diff to max class dummy of class specific recall",
		"highValueBetter": true,
		"isScalarMetric": true,
		"isClassSpecific": false
	  },
	  {
		"id": "min class specific specificity",
		"highValueBetter": true,
		"isScalarMetric": true,
		"isClassSpecific": false
	  },
	  {
		"id": "weighted avg class specific f1score",
		"highValueBetter": false,
		"isScalarMetric": true,
		"isClassSpecific": false
	  },
	  {
		"id": "class specific f0.5score",
		"highValueBetter": false,
		"isScalarMetric": false,
		"isClassSpecific": true
	  },
	  {
		"id": "avg class specific f1score",
		"highValueBetter": false,
		"isScalarMetric": true,
		"isClassSpecific": false
	  },
	  {
		"id": "min class specific recall",
		"highValueBetter": true,
		"isScalarMetric": true,
		"isClassSpecific": false
	  },
	  {
		"id": "class specific recall",
		"highValueBetter": true,
		"isScalarMetric": false,
		"isClassSpecific": true
	  },
	  {
		"id": "avg class specific recall",
		"highValueBetter": true,
		"isScalarMetric": true,
		"isClassSpecific": false
	  },
	  {
		"id": "class specific accuracy",
		"highValueBetter": true,
		"isScalarMetric": false,
		"isClassSpecific": true
	  },
	  {
		"id": "weighted avg class specific accuracy",
		"highValueBetter": true,
		"isScalarMetric": true,
		"isClassSpecific": false
	  },
	  {
		"id": "median class specific f2score",
		"highValueBetter": false,
		"isScalarMetric": true,
		"isClassSpecific": false
	  },
	  {
		"id": "min class specific f2score",
		"highValueBetter": false,
		"isScalarMetric": true,
		"isClassSpecific": false
	  },
	  {
		"id": "max class specific f2score",
		"highValueBetter": false,
		"isScalarMetric": true,
		"isClassSpecific": false
	  },
	  {
		"id": "min class specific f0.5score",
		"highValueBetter": false,
		"isScalarMetric": true,
		"isClassSpecific": false
	  },
	  {
		"id": "weighted avg class specific f2score",
		"highValueBetter": false,
		"isScalarMetric": true,
		"isClassSpecific": false
	  },
	  {
		"id": "avg diff to max class dummy of class specific accuracy",
		"highValueBetter": true,
		"isScalarMetric": true,
		"isClassSpecific": false
	  },
	  {
		"id": "weighted avg class specific specificity",
		"highValueBetter": true,
		"isScalarMetric": true,
		"isClassSpecific": false
	  },
	  {
		"id": "max class specific specificity",
		"highValueBetter": true,
		"isScalarMetric": true,
		"isClassSpecific": false
	  },
	  {
		"id": "median class specific f1score",
		"highValueBetter": false,
		"isScalarMetric": true,
		"isClassSpecific": false
	  },
	  {
		"id": "weighted avg class specific precision",
		"highValueBetter": true,
		"isScalarMetric": true,
		"isClassSpecific": false
	  },
	  {
		"id": "class specific precision",
		"highValueBetter": true,
		"isScalarMetric": false,
		"isClassSpecific": true
	  },
	  {
		"id": "min class specific f1score",
		"highValueBetter": false,
		"isScalarMetric": true,
		"isClassSpecific": false
	  },
	  {
		"id": "avg class specific specificity",
		"highValueBetter": true,
		"isScalarMetric": true,
		"isClassSpecific": false
	  },
	  {
		"id": "weighted avg class specific recall",
		"highValueBetter": true,
		"isScalarMetric": true,
		"isClassSpecific": false
	  },
	  {
		"id": "min class specific accuracy",
		"highValueBetter": true,
		"isScalarMetric": true,
		"isClassSpecific": false
	  }
	]
  }